odoo/addons/hr_leave_hour/README.rst
odoo/addons/hr_leave_hour/__init__.py
odoo/addons/hr_leave_hour/__manifest__.py
odoo/addons/hr_leave_hour/i18n/hr_leave_hour.pot
odoo/addons/hr_leave_hour/i18n/it.po
odoo/addons/hr_leave_hour/models/__init__.py
odoo/addons/hr_leave_hour/models/hr_leave.py
odoo/addons/hr_leave_hour/readme/CONTRIBUTORS.rst
odoo/addons/hr_leave_hour/readme/DESCRIPTION.rst
odoo/addons/hr_leave_hour/readme/USAGE.rst
odoo/addons/hr_leave_hour/static/description/icon.png
odoo/addons/hr_leave_hour/static/description/index.html
odoo/addons/hr_leave_hour/views/hr_leave.xml
odoo13_addon_hr_leave_hour-13.0.1.0.1.dev6.dist-info/METADATA
odoo13_addon_hr_leave_hour-13.0.1.0.1.dev6.dist-info/WHEEL
odoo13_addon_hr_leave_hour-13.0.1.0.1.dev6.dist-info/top_level.txt
odoo13_addon_hr_leave_hour-13.0.1.0.1.dev6.dist-info/RECORD
